plist_tracker/__init__.py
plist_tracker/__main__.py
plist_tracker/cli.py
plist_tracker-0.1.5.dist-info/METADATA
plist_tracker-0.1.5.dist-info/WHEEL
plist_tracker-0.1.5.dist-info/entry_points.txt
plist_tracker-0.1.5.dist-info/RECORD
